paraguay/__init__.py
paraguay/community.py
paraguay/meetup.py
paraguay/telegram.py
paraguay-0.0.1.dist-info/DESCRIPTION.rst
paraguay-0.0.1.dist-info/LICENSE.txt
paraguay-0.0.1.dist-info/METADATA
paraguay-0.0.1.dist-info/RECORD
paraguay-0.0.1.dist-info/WHEEL
paraguay-0.0.1.dist-info/metadata.json
paraguay-0.0.1.dist-info/top_level.txt
