Metadata-Version: 2.0
Name: paraguay
Version: 0.0.1
Summary: Python Paraguay community package
Home-page: https://github.com/pythonparaguay/paraguay
Author: Marcelo Elizeche Landó
Author-email: melizeche@gmail.com
License: UNKNOWN
Project-URL: Website, https://pythonpy.org
Project-URL: Meetup, https://meetup.com/Python-Paraguay
Project-URL: Twitter, https://twitter.com/PythonParaguay
Keywords: python paraguay community comunidad pythonpy this
Platform: UNKNOWN
Classifier: Programming Language :: Python :: 3
Classifier: Programming Language :: Python :: 2.7
Classifier: License :: OSI Approved :: MIT License
Classifier: Operating System :: OS Independent
Classifier: Development Status :: 4 - Beta
Classifier: Intended Audience :: Developers
Classifier: Intended Audience :: Education
